{
 "updated": "2026-06-29T08:31:45Z",
 "sources": {
  "octopus": {
   "status": "vuota",
   "detail": "pagina letta ma 0 offerte (https://octopusenergy.it/le-nostre-tariffe)",
   "n": 0,
   "checked": "2026-06-29T08:30:39Z"
  },
  "enel": {
   "status": "vuota",
   "detail": "pagina letta ma 0 offerte (https://www.enel.it/it/luce-e-gas/luce/offerte)",
   "n": 0,
   "checked": "2026-06-29T08:30:50Z"
  },
  "plenitude": {
   "status": "vuota",
   "detail": "pagina letta ma 0 offerte (https://eniplenitude.com/offerte/casa)",
   "n": 0,
   "checked": "2026-06-29T08:30:59Z"
  },
  "a2a": {
   "status": "vuota",
   "detail": "pagina letta ma 0 offerte (https://www.a2aenergia.eu/offerte-luce-gas)",
   "n": 0,
   "checked": "2026-06-29T08:31:11Z"
  },
  "edison": {
   "status": "vuota",
   "detail": "pagina letta ma 0 offerte (https://www.edisonenergia.it/edison/luce-gas-servizi)",
   "n": 0,
   "checked": "2026-06-29T08:31:24Z"
  },
  "sorgenia": {
   "status": "vuota",
   "detail": "pagina letta ma 0 offerte (https://www.sorgenia.it/offerte-luce-gas-casa)",
   "n": 0,
   "checked": "2026-06-29T08:31:33Z"
  },
  "iren": {
   "status": "vuota",
   "detail": "pagina letta ma 0 offerte (https://www.irenlucegas.it/casa)",
   "n": 0,
   "checked": "2026-06-29T08:31:42Z"
  },
  "energy_charts": {
   "status": "ok",
   "detail": "ultimo 2026-06-29: 0.15747 €/kWh",
   "n": 9,
   "checked": "2026-06-29T08:31:45Z"
  }
 }
}