{
 "updated": "2026-06-13T13:35:05Z",
 "sources": {
  "gas/a2a": {
   "operatore": "A2A Energia",
   "status": "vuoto",
   "detail": "nessuna offerta estratta (vedi artifact debug)",
   "n": 0,
   "updated": "2026-06-13T12:15:08Z"
  },
  "gas/edison": {
   "operatore": "Edison Energia",
   "status": "vuoto",
   "detail": "nessuna offerta estratta (vedi artifact debug)",
   "n": 0,
   "updated": "2026-06-13T12:17:07Z"
  },
  "gas/enel": {
   "operatore": "Enel Energia",
   "status": "vuoto",
   "detail": "nessuna offerta estratta (vedi artifact debug)",
   "n": 0,
   "updated": "2026-06-13T12:11:45Z"
  },
  "gas/iren": {
   "operatore": "Iren Luce Gas e Servizi",
   "status": "vuoto",
   "detail": "nessuna offerta estratta (vedi artifact debug)",
   "n": 0,
   "updated": "2026-06-13T12:20:22Z"
  },
  "gas/octopus": {
   "operatore": "Octopus Energy",
   "status": "vuoto",
   "detail": "nessuna offerta estratta (vedi artifact debug)",
   "n": 0,
   "updated": "2026-06-13T12:24:15Z"
  },
  "gas/plenitude": {
   "operatore": "Plenitude (Eni)",
   "status": "vuoto",
   "detail": "nessuna offerta estratta (vedi artifact debug)",
   "n": 0,
   "updated": "2026-06-13T12:16:04Z"
  },
  "gas/sorgenia": {
   "operatore": "sorgenia",
   "status": "vuoto",
   "detail": "nessuna offerta estratta (vedi artifact debug)",
   "n": 0,
   "updated": "2026-06-13T07:37:08Z"
  },
  "luce/a2a": {
   "operatore": "A2A Energia",
   "status": "vuoto",
   "detail": "nessuna offerta estratta (vedi artifact debug)",
   "n": 0,
   "updated": "2026-06-13T10:42:46Z"
  },
  "luce/edison": {
   "operatore": "Edison Energia",
   "status": "vuoto",
   "detail": "nessuna offerta estratta (vedi artifact debug)",
   "n": 0,
   "updated": "2026-06-13T10:43:39Z"
  },
  "luce/enel": {
   "operatore": "Enel Energia",
   "status": "vuoto",
   "detail": "nessuna offerta estratta (vedi artifact debug)",
   "n": 0,
   "updated": "2026-06-13T10:41:57Z"
  },
  "luce/iren": {
   "operatore": "iren",
   "status": "vuoto",
   "detail": "nessuna offerta estratta (vedi artifact debug)",
   "n": 0,
   "updated": "2026-06-13T07:36:33Z"
  },
  "luce/octopus": {
   "operatore": "octopus",
   "status": "vuoto",
   "detail": "nessuna offerta estratta (vedi artifact debug)",
   "n": 0,
   "updated": "2026-06-13T07:36:39Z"
  },
  "luce/plenitude": {
   "operatore": "Plenitude (Eni)",
   "status": "vuoto",
   "detail": "nessuna offerta estratta (vedi artifact debug)",
   "n": 0,
   "updated": "2026-06-13T13:00:48Z"
  },
  "luce/sorgenia": {
   "operatore": "Sorgenia",
   "status": "vuoto",
   "detail": "nessuna offerta estratta (vedi artifact debug)",
   "n": 0,
   "updated": "2026-06-13T12:10:54Z"
  },
  "mobile/coopvoce": {
   "operatore": "CoopVoce",
   "status": "ok",
   "detail": "",
   "n": 4,
   "updated": "2026-06-13T13:01:33Z"
  },
  "mobile/digi": {
   "operatore": "Digi Mobil",
   "status": "vuoto",
   "detail": "nessuna offerta estratta (vedi artifact debug)",
   "n": 0,
   "updated": "2026-06-13T12:19:22Z"
  },
  "mobile/fastweb": {
   "operatore": "Fastweb",
   "status": "ok",
   "detail": "",
   "n": 4,
   "updated": "2026-06-13T12:58:32Z"
  },
  "mobile/ho": {
   "operatore": "ho. Mobile",
   "status": "ok",
   "detail": "",
   "n": 7,
   "updated": "2026-06-13T13:00:00Z"
  },
  "mobile/iliad": {
   "operatore": "Iliad",
   "status": "ok",
   "detail": "",
   "n": 4,
   "updated": "2026-06-13T12:56:07Z"
  },
  "mobile/kena": {
   "operatore": "Kena Mobile",
   "status": "ok",
   "detail": "",
   "n": 6,
   "updated": "2026-06-13T12:31:44Z"
  },
  "mobile/lycamobile": {
   "operatore": "Lycamobile",
   "status": "vuoto",
   "detail": "nessuna offerta estratta (vedi artifact debug)",
   "n": 0,
   "updated": "2026-06-13T10:14:20Z"
  },
  "mobile/noitel": {
   "operatore": "Noitel",
   "status": "vuoto",
   "detail": "nessuna offerta estratta (vedi artifact debug)",
   "n": 0,
   "updated": "2026-06-13T12:21:59Z"
  },
  "mobile/optima": {
   "operatore": "Optima Mobile",
   "status": "vuoto",
   "detail": "nessuna offerta estratta (vedi artifact debug)",
   "n": 0,
   "updated": "2026-06-13T12:21:00Z"
  },
  "mobile/postemobile": {
   "operatore": "PosteMobile",
   "status": "vuoto",
   "detail": "nessuna offerta estratta (vedi artifact debug)",
   "n": 0,
   "updated": "2026-06-13T07:35:34Z"
  },
  "mobile/sky": {
   "operatore": "Sky Mobile",
   "status": "ok",
   "detail": "",
   "n": 4,
   "updated": "2026-06-13T12:32:25Z"
  },
  "mobile/spusu": {
   "operatore": "spusu",
   "status": "vuoto",
   "detail": "nessuna offerta estratta (vedi artifact debug)",
   "n": 0,
   "updated": "2026-06-13T12:09:48Z"
  },
  "mobile/tim": {
   "operatore": "TIM",
   "status": "vuoto",
   "detail": "nessuna offerta estratta (vedi artifact debug)",
   "n": 0,
   "updated": "2026-06-13T12:57:51Z"
  },
  "mobile/tiscali": {
   "operatore": "Tiscali Mobile",
   "status": "ok",
   "detail": "",
   "n": 3,
   "updated": "2026-06-13T12:12:29Z"
  },
  "mobile/unomobile": {
   "operatore": "1Mobile",
   "status": "vuoto",
   "detail": "nessuna offerta estratta (vedi artifact debug)",
   "n": 0,
   "updated": "2026-06-13T07:35:16Z"
  },
  "mobile/very": {
   "operatore": "Very Mobile",
   "status": "ok",
   "detail": "",
   "n": 2,
   "updated": "2026-06-13T12:30:00Z"
  },
  "mobile/vianova": {
   "operatore": "Vianova",
   "status": "vuoto",
   "detail": "nessuna offerta estratta (vedi artifact debug)",
   "n": 0,
   "updated": "2026-06-13T12:26:01Z"
  },
  "mobile/vodafone": {
   "operatore": "Vodafone",
   "status": "ok",
   "detail": "",
   "n": 4,
   "updated": "2026-06-13T13:34:01Z"
  },
  "mobile/windtre": {
   "operatore": "WindTre",
   "status": "ok",
   "detail": "",
   "n": 6,
   "updated": "2026-06-13T12:59:18Z"
  }
 }
}